pyskna/__init__.py
pyskna/__version__.py
pyskna/_vfcdm.py
pyskna/_vfcdm_installer.py
pyskna/process_iskna.py
pyskna/process_tvskna.py
pyskna-0.1.1.dist-info/licenses/LICENSE.md
pyskna-0.1.1.dist-info/METADATA
pyskna-0.1.1.dist-info/WHEEL
pyskna-0.1.1.dist-info/top_level.txt
pyskna-0.1.1.dist-info/RECORD
