Metadata-Version: 2.4
Name: pyskna
Version: 0.1.1
Summary: This toolbox provides computation methods for skin sympathetic nerve activity (SKNA), which can be derived from electrocardiogram (ECG) signals collected under specific recording conditions.
Author-email: "Youngsun Kong, Ph.D." <youngsun.kong.phd@gmail.com>
License: MIT
Keywords: SKNA,TVSKNA,iSKNA,biosignal,neuroscience,biomedical,MIT,non-commercial
Classifier: License :: OSI Approved :: MIT License
Classifier: Programming Language :: Python :: 3
Classifier: Intended Audience :: Science/Research
Classifier: Topic :: Scientific/Engineering :: Medical Science Apps.
Classifier: Operating System :: Microsoft :: Windows
Classifier: Operating System :: POSIX :: Linux
Classifier: Operating System :: MacOS :: MacOS X
Requires-Python: >=3.7
License-File: LICENSE.md
Requires-Dist: numpy
Requires-Dist: scipy
Dynamic: license-file
